spinsight/__init__.py
spinsight/constants.py
spinsight/deploy.py
spinsight/hoverCallback.js
spinsight/load_phantom.py
spinsight/main.py
spinsight/paramBounds.tex
spinsight/recon.py
spinsight/sequence.py
spinsight/phantoms/Shepp-Logan/Shepp-Logan.toml
spinsight/phantoms/Shepp-Logan/Shepp-Logan_shapes.toml
spinsight/phantoms/abdomen/abdomen.svg
spinsight/phantoms/abdomen/abdomen.toml
spinsight/phantoms/brain/brain.svg
spinsight/phantoms/brain/brain.toml
spinsight-1.2.0.dist-info/METADATA
spinsight-1.2.0.dist-info/WHEEL
spinsight-1.2.0.dist-info/entry_points.txt
spinsight-1.2.0.dist-info/licenses/LICENSE.md
spinsight-1.2.0.dist-info/RECORD
