Metadata-Version: 2.4
Name: spinsight
Version: 1.2.0
Summary: MR image simulator for teaching purposes
Project-URL: Homepage, https://github.com/bretglun/spinsight
Author-email: Johan Berglund <berglund.hpj@gmail.com>
License-Expression: GPL-3.0-or-later
License-File: LICENSE.md
Requires-Python: >=3.10
Requires-Dist: darkdetect>=0.8.0
Requires-Dist: finufft>=2.4.1
Requires-Dist: holoviews>=1.21.0
Requires-Dist: mri-nufft>=1.2.1
Requires-Dist: numpy>=2.2.6
Requires-Dist: panel>=1.8.2
Requires-Dist: param>=2.2.1
Requires-Dist: scipy>=1.15.3
Requires-Dist: svgpathtools>=1.7.1
Requires-Dist: toml>=0.10.2
Requires-Dist: xarray>=2025.6.1
